pyeurovoc/__init__.py
pyeurovoc/model.py
pyeurovoc/util.py
pyeurovoc-1.3.0.dist-info/LICENSE
pyeurovoc-1.3.0.dist-info/METADATA
pyeurovoc-1.3.0.dist-info/WHEEL
pyeurovoc-1.3.0.dist-info/top_level.txt
pyeurovoc-1.3.0.dist-info/RECORD
