Metadata-Version: 2.1
Name: pyeurovoc
Version: 1.3.0
Summary: Python API for multilingual legal document classification with EuroVoc descriptors using BERT models.
Home-page: https://github.com/racai-ai/pyeurovoc
Author: Andrei-Marius Avram, Vasile Pais, Dan Tufis
Author-email: avram.andreimarius@gmail.com
Maintainer: Andrei-Marius Avram
Maintainer-email: avram.andreimarius@gmail.com
Keywords: eurovoc bert legal document classification
Classifier: Development Status :: 5 - Production/Stable
Classifier: Intended Audience :: Developers
Classifier: Intended Audience :: Education
Classifier: Intended Audience :: Information Technology
Classifier: Intended Audience :: Science/Research
Classifier: Topic :: Scientific/Engineering
Classifier: Topic :: Scientific/Engineering :: Human Machine Interfaces
Classifier: Topic :: Scientific/Engineering :: Information Analysis
Classifier: Topic :: Text Processing
Classifier: Topic :: Text Processing :: Filters
Classifier: Topic :: Text Processing :: General
Classifier: Topic :: Text Processing :: Indexing
Classifier: Topic :: Text Processing :: Linguistic
Classifier: License :: OSI Approved :: MIT License
Classifier: Programming Language :: Python :: 3
License-File: LICENSE
Requires-Dist: transformers
Requires-Dist: sklearn
Requires-Dist: torch
Requires-Dist: scikit-multilearn
Requires-Dist: pyyaml
Requires-Dist: waitress
Requires-Dist: flask
